Workbook

Sheet p1
A3: Row Labels | B3: Sum of Sales
A4: East | B4: 181300
A5: North | B5: 86200
A6: South | B6: 82200
A7: West | B7: 154400
A8: Grand Total | B8: 504100

Sheet p2
A3: Row Labels | B3: Sum of Profit
A4: Clothing | B4: 9440
A5: Electronics | B5: 45600
A6: Furniture | B6: 42400
A7: Grand Total | B7: 97440

Sheet Sheet6
A3: Row Labels | B3: Sum of Sales
A4: Feb | B4: 504100
A5: Jan | B5: 504100
A6: Grand Total | B6: 504100

Sheet p3

Sheet Sales data 
A1: Order ID | B1: Date | C1: Region | D1: Category | E1: Product | F1: Sales | G1: Profit | H1: Quantity | I1: Sales Per unit | J1: profit % | K1: Month
A2: 1001 | B2: 45658 | C2: West | D2: Electronics | E2: Laptop | F2: 55000 | G2: 8000 | H2: 2 | I2: =F2/H2 -> 27500 | J2: =G2/F2 -> 0.14545455 | K2: =TEXT(B2,"mmm") -> Jan
A3: 1002 | B3: 45659 | C3: North | D3: Furniture | E3: Chair | F3: 7000 | G3: 1500 | H3: 5 | I3: =F3/H3 -> 1400 | J3: =G3/F3 -> 0.21428571 | K3: =TEXT(B3,"mmm") -> Jan
A4: 1003 | B4: 45660 | C4: South | D4: Clothing | E4: T-Shirt | F4: 2500 | G4: 500 | H4: 10 | I4: =F4/H4 -> 250 | J4: =G4/F4 -> 0.2 | K4: =TEXT(B4,"mmm") -> Jan
A5: 1004 | B5: 45661 | C5: East | D5: Electronics | E5: Mobile | F5: 30000 | G5: 6000 | H5: 3 | I5: =F5/H5 -> 10000 | J5: =G5/F5 -> 0.2 | K5: =TEXT(B5,"mmm") -> Jan
A6: 1005 | B6: 45662 | C6: West | D6: Furniture | E6: Table | F6: 12000 | G6: 2500 | H6: 2 | I6: =F6/H6 -> 6000 | J6: =G6/F6 -> 0.20833333 | K6: =TEXT(B6,"mmm") -> Jan
A7: 1006 | B7: 45663 | C7: North | D7: Electronics | E7: Headphones | F7: 4000 | G7: 800 | H7: 4 | I7: =F7/H7 -> 1000 | J7: =G7/F7 -> 0.2 | K7: =TEXT(B7,"mmm") -> Jan
A8: 1007 | B8: 45664 | C8: South | D8: Clothing | E8: Jeans | F8: 3500 | G8: 700 | H8: 6 | I8: =F8/H8 -> 583.33333 | J8: =G8/F8 -> 0.2 | K8: =TEXT(B8,"mmm") -> Jan
A9: 1008 | B9: 45665 | C9: East | D9: Electronics | E9: TV | F9: 45000 | G9: 9000 | H9: 1 | I9: =F9/H9 -> 45000 | J9: =G9/F9 -> 0.2 | K9: =TEXT(B9,"mmm") -> Jan
A10: 1009 | B10: 45666 | C10: West | D10: Furniture | E10: Sofa | F10: 25000 | G10: 5000 | H10: 1 | I10: =F10/H10 -> 25000 | J10: =G10/F10 -> 0.2 | K10: =TEXT(B10,"mmm") -> Jan
A11: 1010 | B11: 45667 | C11: North | D11: Clothing | E11: Jacket | F11: 5000 | G11: 1000 | H11: 3 | I11: =F11/H11 -> 1666.6667 | J11: =G11/F11 -> 0.2 | K11: =TEXT(B11,"mmm") -> Jan
A12: 1011 | B12: 45668 | C12: South | D12: Electronics | E12: Smart Watch | F12: 15000 | G12: 3000 | H12: 2 | I12: =F12/H12 -> 7500 | J12: =G12/F12 -> 0.2 | K12: =TEXT(B12,"mmm") -> Jan
A13: 1012 | B13: 45669 | C13: East | D13: Furniture | E13: Bed | F13: 35000 | G13: 7000 | H13: 1 | I13: =F13/H13 -> 35000 | J13: =G13/F13 -> 0.2 | K13: =TEXT(B13,"mmm") -> Jan
... A41: 1040 | B41: 45697 | C41: East | D41: Clothing | E41: Sweater | F41: 3800 | G41: 760 | H41: 3 | I41: =F41/H41 -> 1266.6667 | J41: =G41/F41 -> 0.2 | K41: =TEXT(B41,"mmm") -> Feb

Sheet Dashboard 
A1: Sales Data Report
E3: Total Sales | G3: Total Profit | I3: Total Quantity | K3: Average Sales | M3: Total Orders
E5: =SUM('Sales data '!F:F) -> 504100 | G5: =SUM('Sales data '!G:G) -> 97440 | I5: =SUM('Sales data '!H:H) -> 139 | K5: =AVERAGE('Sales data '!F:F) -> 12602.5 | M5: =COUNTA('Sales data '!A2:A41) -> 40

Sheet Business Insight
D1: Business Insights
D4: 1 | E4: Identified East region as the highest revenue contributor (₹181K+ sales).
D5: 2 | E5: Discovered Electronics category generated the highest profit (₹45.6K).
D6: 3 | E6: Analyzed product-level performance and identified top-selling products.
D7: 4 | E7: Calculated KPIs including Total Sales (₹504K), Profit (₹97K), and Profit Margin (19.3%).
D8: 5 | E8: Provided data-driven recommendations for sales growth and inventory optimization.
